movesymlink.py
movesymlink-0.1.0.dist-info/DESCRIPTION.rst
movesymlink-0.1.0.dist-info/METADATA
movesymlink-0.1.0.dist-info/RECORD
movesymlink-0.1.0.dist-info/WHEEL
movesymlink-0.1.0.dist-info/entry_points.txt
movesymlink-0.1.0.dist-info/metadata.json
movesymlink-0.1.0.dist-info/top_level.txt
