Metadata-Version: 2.0
Name: movesymlink
Version: 0.1.0
Summary: Move Symlink provides a function and a command that moves a symbolic link to another directory and adjusts its link target.
Home-page: https://github.com/astralblue/movesymlink
Author: Eugene M. Kim
Author-email: astralblue@gmail.com
License: MIT license
Keywords: movesymlink
Platform: UNKNOWN
Classifier: Development Status :: 2 - Pre-Alpha
Classifier: Intended Audience :: Developers
Classifier: License :: OSI Approved :: MIT License
Classifier: Natural Language :: English
Classifier: Programming Language :: Python :: 3
Classifier: Programming Language :: Python :: 3.4
Classifier: Programming Language :: Python :: 3.5
Classifier: Programming Language :: Python :: 3.6
